Metadata-Version: 2.1
Name: cryplimp
Version: 1.35
Summary: cryptography library
Home-page: https://github.com/KingfernJohn/cryplimp
Author: KingfernJohn
Author-email: kingfernjohn@gmail.com
Keywords: python,cryptography,encrypt,decrypt
Classifier: Development Status :: 5 - Production/Stable
Classifier: Intended Audience :: Developers
Classifier: License :: OSI Approved :: MIT License
Classifier: Programming Language :: Python :: 3
Classifier: Programming Language :: Python :: 3.6
Classifier: Programming Language :: Python :: 3.7
Classifier: Programming Language :: Python :: 3.8
Classifier: Programming Language :: Python :: 3.9
License-File: LICENSE
